django_tokenauth-0.5.5.dist-info/licenses/LICENSE
tokenauth/__init__.py
tokenauth/admin.py
tokenauth/apps.py
tokenauth/auth_backends.py
tokenauth/helpers.py
tokenauth/models.py
tokenauth/settings.py
tokenauth/urls.py
tokenauth/views.py
tokenauth/migrations/0001_initial.py
tokenauth/migrations/0002_authtoken_next_url.py
tokenauth/migrations/0003_authtoken_new_email.py
tokenauth/migrations/0004_add_email_log.py
tokenauth/migrations/__init__.py
tokenauth/templates/tokenauth_change_body.txt
tokenauth/templates/tokenauth_change_subject.txt
tokenauth/templates/tokenauth_login_body.txt
tokenauth/templates/tokenauth_login_subject.txt
django_tokenauth-0.5.5.dist-info/METADATA
django_tokenauth-0.5.5.dist-info/WHEEL
django_tokenauth-0.5.5.dist-info/top_level.txt
django_tokenauth-0.5.5.dist-info/RECORD
